muxi/runtime/.version
muxi/runtime/__init__.py
muxi/runtime/datatypes/__init__.py
muxi/runtime/datatypes/api.py
muxi/runtime/datatypes/artifacts.py
muxi/runtime/datatypes/async_operations.py
muxi/runtime/datatypes/clarification.py
muxi/runtime/datatypes/errors.py
muxi/runtime/datatypes/exceptions.py
muxi/runtime/datatypes/intent.py
muxi/runtime/datatypes/json_type.py
muxi/runtime/datatypes/llm.py
muxi/runtime/datatypes/mcp.py
muxi/runtime/datatypes/memory.py
muxi/runtime/datatypes/observability.py
muxi/runtime/datatypes/resilience.py
muxi/runtime/datatypes/response.py
muxi/runtime/datatypes/retry.py
muxi/runtime/datatypes/schema.py
muxi/runtime/datatypes/task_status.py
muxi/runtime/datatypes/type_definitions.py
muxi/runtime/datatypes/validation.py
muxi/runtime/datatypes/workflow.py
muxi/runtime/datatypes/workflow_models.py
muxi/runtime/extensions/__init__.py
muxi/runtime/extensions/base.py
muxi/runtime/extensions/sqlite_vec.py
muxi/runtime/extensions/loadable/__init__.py
muxi/runtime/extensions/loadable/sqlite-vec/__init__.py
muxi/runtime/extensions/loadable/sqlite-vec/arm64-darwin/vec0.dylib
muxi/runtime/extensions/loadable/sqlite-vec/arm64-linux/vec0.so
muxi/runtime/extensions/loadable/sqlite-vec/x86_64-darwin/vec0.dylib
muxi/runtime/extensions/loadable/sqlite-vec/x86_64-linux/vec0.so
muxi/runtime/extensions/loadable/sqlite-vec/x86_64-windows/vec0.dll
muxi/runtime/formation/__init__.py
muxi/runtime/formation/formation.py
muxi/runtime/formation/initialization.py
muxi/runtime/formation/runtime_agent_processor.py
muxi/runtime/formation/agents/__init__.py
muxi/runtime/formation/agents/agent.py
muxi/runtime/formation/agents/generalist.yaml
muxi/runtime/formation/agents/knowledge/__init__.py
muxi/runtime/formation/agents/knowledge/base.py
muxi/runtime/formation/agents/knowledge/handler.py
muxi/runtime/formation/artifacts/__init__.py
muxi/runtime/formation/artifacts/artifact_service.py
muxi/runtime/formation/artifacts/extractor.py
muxi_runtime-0.20260201.1.dist-info/licenses/LICENSE
muxi_runtime-0.20260201.1.dist-info/METADATA
muxi_runtime-0.20260201.1.dist-info/WHEEL
muxi_runtime-0.20260201.1.dist-info/top_level.txt
muxi_runtime-0.20260201.1.dist-info/RECORD
